denodo_extractor/__init__.py
denodo_extractor/__main__.py
denodo_extractor/connector.py
denodo_extractor/extractor.py
denodo_extractor-0.0.1.dist-info/METADATA
denodo_extractor-0.0.1.dist-info/WHEEL
denodo_extractor-0.0.1.dist-info/top_level.txt
denodo_extractor-0.0.1.dist-info/RECORD
