Metadata-Version: 2.4
Name: denodo_extractor
Version: 0.0.1
Summary: A package to extract metadata from a Denodo workspace
Author-email: Eduard Ma <eduardma1999@proton.me>
License-Expression: MIT
Project-URL: Homepage, https://github.com/MaEduard/denodo_extractor
Project-URL: Issues, https://github.com/MaEduard/denodo_extractor/issues
Classifier: Programming Language :: Python :: 3
Classifier: Operating System :: OS Independent
Requires-Python: >=3.9
